{
  "id": 1661548886046,
  "title": "Poderoso Deus Eterno",
  "artist": "Davi Silva",
  "author": "Davi Silva",
  "note": "",
  "copyright": "",
  "key": "",
  "bpm": 0.0,
  "time_sig": "",
  "midi": null,
  "order": "",
  "lyrics": {
    "full_text": "Anjos proclamam\nA Tua majestade\nProstrado aos Teus pés\nAdorando ao Rei\n\nTerra e Céu cantarão\nUma canção que se ouvirá\nDeclarando: \"Santo\"\n\nSua glória descerá\nSobre a Terra se espalhará\nEm uma só voz cantando\nTe entronizando\n\nSanto, Poderoso\nDeus Eterno\nQue é, que há de vir\nEm glória\n2x\n\nTerra e Céu cantarão\nUma canção que se ouvirá\nDeclarando: \"Santo\"\n\nSua glória descerá\nSobre a Terra se espalhará\nEm uma só voz cantando\nTe entronizando\n\nSanto, Poderoso\nDeus Eterno\nQue é, que há de vir\nEm glória\n3x\n\nAleluia\nAleluia\nAleluia\nAleluia\nAleluia\nAleluia\nAleluia\nAleluia",
    "full_text_with_comment": null,
    "paragraphs": [
      {
        "number": 1,
        "description": "",
        "text": "Anjos proclamam\nA Tua majestade\nProstrado aos Teus pés\nAdorando ao Rei",
        "text_with_comment": null,
        "translations": null
      },
      {
        "number": 2,
        "description": "",
        "text": "Terra e Céu cantarão\nUma canção que se ouvirá\nDeclarando: \"Santo\"",
        "text_with_comment": null,
        "translations": null
      },
      {
        "number": 3,
        "description": "",
        "text": "Sua glória descerá\nSobre a Terra se espalhará\nEm uma só voz cantando\nTe entronizando",
        "text_with_comment": null,
        "translations": null
      },
      {
        "number": 4,
        "description": "",
        "text": "Santo, Poderoso\nDeus Eterno\nQue é, que há de vir\nEm glória\n2x",
        "text_with_comment": null,
        "translations": null
      },
      {
        "number": 5,
        "description": "",
        "text": "Terra e Céu cantarão\nUma canção que se ouvirá\nDeclarando: \"Santo\"",
        "text_with_comment": null,
        "translations": null
      },
      {
        "number": 6,
        "description": "",
        "text": "Sua glória descerá\nSobre a Terra se espalhará\nEm uma só voz cantando\nTe entronizando",
        "text_with_comment": null,
        "translations": null
      },
      {
        "number": 7,
        "description": "",
        "text": "Santo, Poderoso\nDeus Eterno\nQue é, que há de vir\nEm glória\n3x",
        "text_with_comment": null,
        "translations": null
      },
      {
        "number": 8,
        "description": "",
        "text": "Aleluia\nAleluia\nAleluia\nAleluia\nAleluia\nAleluia\nAleluia\nAleluia",
        "text_with_comment": null,
        "translations": null
      }
    ]
  },
  "streaming": {
    "audio": {
      "spotify": "",
      "youtube": "",
      "deezer": ""
    },
    "backing_track": {
      "spotify": "",
      "youtube": "",
      "deezer": ""
    }
  },
  "extras": {
    "extra": ""
  }
}