{
  "id": 1653227048247,
  "title": "Seja Forte",
  "artist": "Isadora Pompeo",
  "author": "Isadora Pompeo",
  "note": "",
  "copyright": "",
  "key": "",
  "bpm": 0.0,
  "time_sig": "",
  "midi": null,
  "order": "",
  "lyrics": {
    "full_text": "A solidão vem\nE ela quer me destruir\nE o pânico me fala que\nEu não posso mais sorrir\n\nMe sinto preso\nEm mim mesmo\nNão sei de onde veio\nTodo esse medo\n\nE a culpa quer me convencer\nDe que isso vem de mim\nPondo pensamentos\nDe que não é fácil assim\n\nQue eu devo sonhar menos\nPoupar os meus talentos\nMas isso não é o que\nO meu Pai diz pra mim\n\nEu ouço a Sua voz, Deus\nEu ouço a Sua voz, Deus\nEu ouço a Sua voz, Deus\nEu ouço a Sua voz, Deus\nDizendo pra mim\n\nSeja forte e corajoso\nNão temas e não desanimes\nEu Sou teu Deus\nTe escondo em Mim\n(2x)\n\nE vai ser sempre assim\n(2x)\n\nEu ouço a Sua voz, Deus\nEu ouço a Sua voz, Deus\nEu ouço a Sua voz, Deus\nEu ouço a Sua voz, Deus\nDizendo pra mim\n\nSeja forte e corajoso\nNão temas e não desanimes\nEu Sou teu Deus\nTe escondo em Mim\n(2x)\n\nE vai ser sempre assim\n(4x)\n\nSeja forte e corajoso\nNão temas e não desanimes\nEu Sou teu Deus\nTe escondo em Mim\nSeja forte e corajoso...",
    "full_text_with_comment": null,
    "paragraphs": [
      {
        "number": 1,
        "description": "",
        "text": "A solidão vem\nE ela quer me destruir\nE o pânico me fala que\nEu não posso mais sorrir",
        "text_with_comment": null,
        "translations": null
      },
      {
        "number": 2,
        "description": "",
        "text": "Me sinto preso\nEm mim mesmo\nNão sei de onde veio\nTodo esse medo",
        "text_with_comment": null,
        "translations": null
      },
      {
        "number": 3,
        "description": "",
        "text": "E a culpa quer me convencer\nDe que isso vem de mim\nPondo pensamentos\nDe que não é fácil assim",
        "text_with_comment": null,
        "translations": null
      },
      {
        "number": 4,
        "description": "",
        "text": "Que eu devo sonhar menos\nPoupar os meus talentos\nMas isso não é o que\nO meu Pai diz pra mim",
        "text_with_comment": null,
        "translations": null
      },
      {
        "number": 5,
        "description": "",
        "text": "Eu ouço a Sua voz, Deus\nEu ouço a Sua voz, Deus\nEu ouço a Sua voz, Deus\nEu ouço a Sua voz, Deus\nDizendo pra mim",
        "text_with_comment": null,
        "translations": null
      },
      {
        "number": 6,
        "description": "",
        "text": "Seja forte e corajoso\nNão temas e não desanimes\nEu Sou teu Deus\nTe escondo em Mim\n(2x)",
        "text_with_comment": null,
        "translations": null
      },
      {
        "number": 7,
        "description": "",
        "text": "E vai ser sempre assim\n(2x)",
        "text_with_comment": null,
        "translations": null
      },
      {
        "number": 8,
        "description": "",
        "text": "Eu ouço a Sua voz, Deus\nEu ouço a Sua voz, Deus\nEu ouço a Sua voz, Deus\nEu ouço a Sua voz, Deus\nDizendo pra mim",
        "text_with_comment": null,
        "translations": null
      },
      {
        "number": 9,
        "description": "",
        "text": "Seja forte e corajoso\nNão temas e não desanimes\nEu Sou teu Deus\nTe escondo em Mim\n(2x)",
        "text_with_comment": null,
        "translations": null
      },
      {
        "number": 10,
        "description": "",
        "text": "E vai ser sempre assim\n(4x)",
        "text_with_comment": null,
        "translations": null
      },
      {
        "number": 11,
        "description": "",
        "text": "Seja forte e corajoso\nNão temas e não desanimes\nEu Sou teu Deus\nTe escondo em Mim\nSeja forte e corajoso...",
        "text_with_comment": null,
        "translations": null
      }
    ]
  },
  "streaming": {
    "audio": {
      "spotify": "",
      "youtube": "",
      "deezer": ""
    },
    "backing_track": {
      "spotify": "",
      "youtube": "",
      "deezer": ""
    }
  },
  "extras": {
    "extra": ""
  }
}