{
  "id": 1681688450779,
  "title": "Vem Com Josué Lutar Em Jericó",
  "artist": "Eli Soares",
  "author": "",
  "note": "",
  "copyright": "",
  "key": "",
  "bpm": 0.0,
  "time_sig": "",
  "midi": null,
  "order": "",
  "lyrics": {
    "full_text": "Vem com Josué lutar em Jericó\nJericó, Jericó\nVem com Josué lutar em Jericó\nE as muralhas ruirão\n\nVem com Josué lutar em Jericó\nJericó, Jericó\nVem com Josué lutar em Jericó\nE as muralhas ruirão\n\nSuba os montes devagar\nQue o senhor vai guerrear\nCerquem os muros para mim\nPois, Jericó chegou ao fim, vem, vem, vem\n\nVem com Josué lutar em Jericó\nJericó, Jericó\nVem com Josué lutar em Jericó\nE as muralhas ruirão\n\nVem com Josué lutar em Jericó\nJericó, Jericó\nVem com Josué lutar em Jericó\nE as muralhas ruirão\n\nAs trombetas soarão\nAbalando o céu e o chão\nCerquem os muros para mim\nPois, Jericó chegou ao fim, vem, vem, vem\n\nVem com Josué lutar em Jericó\nJericó, Jericó\nVem com Josué lutar em Jericó\nE as muralhas ruirão\n\nE as muralhas ruirão\nE as muralhas ruirão",
    "full_text_with_comment": null,
    "paragraphs": [
      {
        "number": 1,
        "description": "",
        "text": "Vem com Josué lutar em Jericó\nJericó, Jericó\nVem com Josué lutar em Jericó\nE as muralhas ruirão",
        "text_with_comment": null,
        "translations": null
      },
      {
        "number": 2,
        "description": "",
        "text": "Vem com Josué lutar em Jericó\nJericó, Jericó\nVem com Josué lutar em Jericó\nE as muralhas ruirão",
        "text_with_comment": null,
        "translations": null
      },
      {
        "number": 3,
        "description": "",
        "text": "Suba os montes devagar\nQue o senhor vai guerrear\nCerquem os muros para mim\nPois, Jericó chegou ao fim, vem, vem, vem",
        "text_with_comment": null,
        "translations": null
      },
      {
        "number": 4,
        "description": "",
        "text": "Vem com Josué lutar em Jericó\nJericó, Jericó\nVem com Josué lutar em Jericó\nE as muralhas ruirão",
        "text_with_comment": null,
        "translations": null
      },
      {
        "number": 5,
        "description": "",
        "text": "Vem com Josué lutar em Jericó\nJericó, Jericó\nVem com Josué lutar em Jericó\nE as muralhas ruirão",
        "text_with_comment": null,
        "translations": null
      },
      {
        "number": 6,
        "description": "",
        "text": "As trombetas soarão\nAbalando o céu e o chão\nCerquem os muros para mim\nPois, Jericó chegou ao fim, vem, vem, vem",
        "text_with_comment": null,
        "translations": null
      },
      {
        "number": 7,
        "description": "",
        "text": "Vem com Josué lutar em Jericó\nJericó, Jericó\nVem com Josué lutar em Jericó\nE as muralhas ruirão",
        "text_with_comment": null,
        "translations": null
      },
      {
        "number": 8,
        "description": "",
        "text": "E as muralhas ruirão\nE as muralhas ruirão",
        "text_with_comment": null,
        "translations": null
      }
    ]
  },
  "streaming": {
    "audio": {
      "spotify": "",
      "youtube": "",
      "deezer": ""
    },
    "backing_track": {
      "spotify": "",
      "youtube": "",
      "deezer": ""
    }
  },
  "extras": {
    "extra": ""
  }
}